yatrash/__init__.py
yatrash/__main__.py
yatrash/main.py
yatrash/trash.py
yatrash-0.1.3.dist-info/LICENSE
yatrash-0.1.3.dist-info/METADATA
yatrash-0.1.3.dist-info/WHEEL
yatrash-0.1.3.dist-info/entry_points.txt
yatrash-0.1.3.dist-info/top_level.txt
yatrash-0.1.3.dist-info/RECORD
