Metadata-Version: 2.1
Name: yatrash
Version: 0.1.3
Summary: Safely move files into a trash can instead of `rm`.
Home-page: https://github.com/charmoniumQ/yatrash/
Author: Samuel Grayson
Author-email: sam@samgrayson.me
Classifier: Natural Language :: English
Classifier: Environment :: Console
Classifier: License :: OSI Approved :: GNU General Public License v3 (GPLv3)
Classifier: Operating System :: OS Independent
Classifier: Programming Language :: Python :: 3.6
Classifier: Topic :: Utilities
Requires-Python: >=3.6.0
License-File: LICENSE
